ytimg/__init__.py
ytimg-1.1.dist-info/METADATA
ytimg-1.1.dist-info/WHEEL
ytimg-1.1.dist-info/top_level.txt
ytimg-1.1.dist-info/RECORD
