Metadata-Version: 2.1
Name: ytimg
Version: 1.1
Summary: Gets thumbail of a Youtube video
Home-page: https://github.com/Potatochips2001/ytimg
Author: Potatochips2001
Author-email: 
License: UNKNOWN
Platform: UNKNOWN
Classifier: Programming Language :: Python :: 3
Classifier: License :: OSI Approved :: MIT License
Classifier: Operating System :: OS Independent
Requires-Python: >=3.6
